Metadata-Version: 1.0
Name: distributionsGB
Version: 0.1
Summary: Gaussian and binomial distributions
Home-page: UNKNOWN
Author: Carolina Negrelli
Author-email: caro.negrelli@gmail.com
License: UNKNOWN
Platform: UNKNOWN
